sl/__init__.py
sl/postgresql_adpter.py
test/__init__.py
test/sl/__init__.py
test/sl/test_postgresql_adpter.py
airtech_shared_libery-0.1.dist-info/METADATA
airtech_shared_libery-0.1.dist-info/WHEEL
airtech_shared_libery-0.1.dist-info/top_level.txt
airtech_shared_libery-0.1.dist-info/RECORD
