Metadata-Version: 2.1
Name: airtech-shared-libery
Version: 0.1
Summary: Minha biblioteca compartilhada
Author: Airtech
License: MIT
Requires-Dist: bleach ==6.0.0
Requires-Dist: certifi ==2023.7.22
Requires-Dist: cffi ==1.15.1
Requires-Dist: charset-normalizer ==3.2.0
Requires-Dist: cryptography ==41.0.3
Requires-Dist: distlib ==0.3.7
Requires-Dist: docutils ==0.20.1
Requires-Dist: exceptiongroup ==1.1.2
Requires-Dist: filelock ==3.12.2
Requires-Dist: idna ==3.4
Requires-Dist: importlib-metadata ==6.8.0
Requires-Dist: iniconfig ==2.0.0
Requires-Dist: jaraco.classes ==3.3.0
Requires-Dist: jeepney ==0.8.0
Requires-Dist: keyring ==24.2.0
Requires-Dist: markdown-it-py ==3.0.0
Requires-Dist: mdurl ==0.1.2
Requires-Dist: more-itertools ==10.1.0
Requires-Dist: packaging ==23.1
Requires-Dist: pipenv ==2023.7.23
Requires-Dist: pkginfo ==1.9.6
Requires-Dist: platformdirs ==3.10.0
Requires-Dist: pluggy ==1.2.0
Requires-Dist: psycopg2 ==2.9.7
Requires-Dist: pycparser ==2.21
Requires-Dist: Pygments ==2.16.1
Requires-Dist: pytest ==7.4.0
Requires-Dist: readme-renderer ==40.0
Requires-Dist: requests ==2.31.0
Requires-Dist: requests-toolbelt ==1.0.0
Requires-Dist: rfc3986 ==2.0.0
Requires-Dist: rich ==13.5.2
Requires-Dist: SecretStorage ==3.3.3
Requires-Dist: six ==1.16.0
Requires-Dist: tomli ==2.0.1
Requires-Dist: twine ==4.0.2
Requires-Dist: urllib3 ==2.0.4
Requires-Dist: virtualenv ==20.24.2
Requires-Dist: virtualenv-clone ==0.5.7
Requires-Dist: webencodings ==0.5.1
Requires-Dist: zipp ==3.16.2
